CHANGELOG.md
LICENSE.txt
MANIFEST.in
README.md
requirements.txt
setup.cfg
setup.py
yatadis/__init__.py
yatadis/yatadis.py
yatadis.egg-info/PKG-INFO
yatadis.egg-info/SOURCES.txt
yatadis.egg-info/dependency_links.txt
yatadis.egg-info/entry_points.txt
yatadis.egg-info/requires.txt
yatadis.egg-info/top_level.txt