Metadata-Version: 1.0
Name: yatadis
Version: 0.4.1
Summary: Yet Another Terraform Ansible Dynamic Inventory Script
Home-page: https://github.com/wtsi-hgi/yatadis
Author: UNKNOWN
Author-email: UNKNOWN
License: GPL3
Platform: UNKNOWN
